<annotation>
	<folder>Mask</folder>
	<filename>mask_046.png</filename>
	<path>G:\Shreyas\Deep Learning\Projects\Mask Detection\Dataset\Mask\mask_046.png</path>
	<source>
		<database>Unknown</database>
	</source>
	<size>
		<width>224</width>
		<height>224</height>
		<depth>3</depth>
	</size>
	<segmented>0</segmented>
	<object>
		<name>mask</name>
		<pose>Unspecified</pose>
		<truncated>0</truncated>
		<difficult>0</difficult>
		<bndbox>
			<xmin>27</xmin>
			<ymin>42</ymin>
			<xmax>40</xmax>
			<ymax>61</ymax>
		</bndbox>
	</object>
	<object>
		<name>mask</name>
		<pose>Unspecified</pose>
		<truncated>0</truncated>
		<difficult>0</difficult>
		<bndbox>
			<xmin>40</xmin>
			<ymin>43</ymin>
			<xmax>50</xmax>
			<ymax>60</ymax>
		</bndbox>
	</object>
	<object>
		<name>mask</name>
		<pose>Unspecified</pose>
		<truncated>0</truncated>
		<difficult>0</difficult>
		<bndbox>
			<xmin>106</xmin>
			<ymin>47</ymin>
			<xmax>116</xmax>
			<ymax>65</ymax>
		</bndbox>
	</object>
	<object>
		<name>mask</name>
		<pose>Unspecified</pose>
		<truncated>0</truncated>
		<difficult>0</difficult>
		<bndbox>
			<xmin>87</xmin>
			<ymin>45</ymin>
			<xmax>99</xmax>
			<ymax>65</ymax>
		</bndbox>
	</object>
	<object>
		<name>mask</name>
		<pose>Unspecified</pose>
		<truncated>0</truncated>
		<difficult>0</difficult>
		<bndbox>
			<xmin>160</xmin>
			<ymin>46</ymin>
			<xmax>173</xmax>
			<ymax>66</ymax>
		</bndbox>
	</object>
	<object>
		<name>mask</name>
		<pose>Unspecified</pose>
		<truncated>0</truncated>
		<difficult>0</difficult>
		<bndbox>
			<xmin>175</xmin>
			<ymin>53</ymin>
			<xmax>188</xmax>
			<ymax>72</ymax>
		</bndbox>
	</object>
</annotation>
